MANIFEST.in
README.md
setup.cfg
setup.py
dds_pylib/__init__.py
dds_pylib/dates.py
dds_pylib.egg-info/PKG-INFO
dds_pylib.egg-info/SOURCES.txt
dds_pylib.egg-info/dependency_links.txt
dds_pylib.egg-info/top_level.txt
dds_pylib/ashell_orm/__init__.py
dds_pylib/ashell_orm/ash_fields.py
dds_pylib/ashell_orm/models_orm.py
dds_pylib/decorators/__init__.py
dds_pylib/decorators/annotate.py
dds_pylib/decorators/deprecated.py
dds_pylib/decorators/memoize.py
dds_pylib/decorators/static_vars.py
dds_pylib/decorators/time_decorators.py
dds_pylib/pyext/__init__.py
dds_pylib/pyext/collection.py
dds_pylib/pyext/multigetattr.py
dds_pylib/pyext/nearly_equal.py
dds_pylib/pyext/objects.py
dds_pylib/pyext/struct.py
dds_pylib/test/__init__.py
dds_pylib/test/test_dates.py
dds_pylib/test/test_decorators.py
dds_pylib/test/test_import.py
dds_pylib/test/test_pyext.py
dds_pylib/test/test_pyext_collection.py
dds_pylib/test/test_pyext_objects.py
dds_pylib/test/test_util.py
dds_pylib/util/__init__.py
dds_pylib/util/case.py
dds_pylib/util/clear_screen.py
dds_pylib/util/print_pythonpath.py